Metadata-Version: 2.1
Name: fthelper
Version: 0.1.2
Summary: Dict, list and string helper package
Home-page: https://gitlab.com/fatihirday/fthelper
Author: Fatih IRDAY
Author-email: fatihirday@gmail.com
License: UNKNOWN
Platform: UNKNOWN
Classifier: Programming Language :: Python :: 3.6
Classifier: License :: OSI Approved :: MIT License
Classifier: Operating System :: OS Independent
Requires-Python: >=3.6
